[
  {
    "id": 1,
    "priority": 1,
    "action": {
      "type": "modifyHeaders",
      "requestHeaders": [
        { "header": "origin", "operation": "set", "value": "https://www.youtube.com" },
        { "header": "referer", "operation": "set", "value": "https://www.youtube.com/" }
      ]
    },
    "condition": {
      "urlFilter": "||youtube.com/youtubei/v1/",
      "resourceTypes": ["xmlhttprequest", "other"]
    }
  },
  {
    "id": 2,
    "priority": 1,
    "action": {
      "type": "modifyHeaders",
      "requestHeaders": [
        { "header": "origin", "operation": "set", "value": "https://www.youtube.com" },
        { "header": "referer", "operation": "set", "value": "https://www.youtube.com/" }
      ]
    },
    "condition": {
      "urlFilter": "||youtube.com/api/timedtext",
      "resourceTypes": ["xmlhttprequest", "other"]
    }
  }
]
